affixr/__init__.py
affixr-1.0.0.dist-info/licenses/LICENSE
affixr-1.0.0.dist-info/METADATA
affixr-1.0.0.dist-info/WHEEL
affixr-1.0.0.dist-info/top_level.txt
affixr-1.0.0.dist-info/RECORD
